Metadata-Version: 2.1
Name: biopython.convert
Version: 1.3.3
Summary: Interconvert various file formats supported by biopython. Supports querying records with JMESPath.
Home-page: https://github.com/brinkmanlab/biopython-convert
Author: Nolan Woods
Author-email: nolan_w@sfu.ca
License: MIT Amended
Keywords: convert,biopython,bioinformatics,gff,genbank,embl,filter,fasta,fastq
Platform: UNKNOWN
Classifier: Environment :: Console
Classifier: Intended Audience :: Science/Research
Classifier: License :: OSI Approved :: MIT License
Classifier: Operating System :: POSIX
Classifier: Programming Language :: Python :: 3.7
Classifier: Topic :: Scientific/Engineering :: Bio-Informatics
License-File: LICENCE.rst
